unicef_djangolib/__init__.py
unicef_djangolib/admin_utils.py
unicef_djangolib/fields.py
unicef_djangolib/forms.py
unicef_djangolib/middleware.py
unicef_djangolib/templates/403.html
unicef_djangolib/templates/404.html
unicef_djangolib/templates/500.html
unicef_djangolib/templates/_base.html
unicef_djangolib/templates/includes/footer.html
unicef_djangolib/templates/includes/header.html
unicef_djangolib/templatetags/djangolib.py
unicef_djangolib-0.7.dist-info/LICENSE
unicef_djangolib-0.7.dist-info/METADATA
unicef_djangolib-0.7.dist-info/WHEEL
unicef_djangolib-0.7.dist-info/top_level.txt
unicef_djangolib-0.7.dist-info/RECORD
