Metadata-Version: 2.1
Name: unicef-djangolib
Version: 0.7
Summary: Django package that handles exporting of data
Home-page: https://github.com/unicef/unicef-djangolib
Author: UNICEF
Author-email: dev@unicef.org
License: Apache 2 License
Platform: any
Classifier: Environment :: Web Environment
Classifier: Programming Language :: Python :: 3.9
Classifier: Framework :: Django
Classifier: Framework :: Django :: 4.0
Classifier: Intended Audience :: Developers
License-File: LICENSE
Requires-Dist: Django
Requires-Dist: django-fsm
Requires-Dist: django-model-utils
Provides-Extra: test
Requires-Dist: factory-boy ; extra == 'test'
Requires-Dist: flake8 ; extra == 'test'
Requires-Dist: isort ; extra == 'test'
Requires-Dist: pytest ; extra == 'test'
Requires-Dist: pytest-cov ; extra == 'test'
Requires-Dist: pytest-django ; extra == 'test'
Requires-Dist: pytest-echo ; extra == 'test'
Requires-Dist: pdbpp ; extra == 'test'
